garnets/__init__.py
garnets/reader.py
garnets/trajectory.py
garnets/version.py
garnets/writer.py
garnets-0.1.0.dist-info/LICENSE
garnets-0.1.0.dist-info/METADATA
garnets-0.1.0.dist-info/WHEEL
garnets-0.1.0.dist-info/top_level.txt
garnets-0.1.0.dist-info/RECORD
