Metadata-Version: 2.1
Name: garnets
Version: 0.1.0
Summary: Simple adapter to smooth API transitions of the garnett project
Home-page: UNKNOWN
Author: Matthew Spellings
Author-email: matthew.p.spellings@gmail.com
License: MIT
Platform: UNKNOWN
Classifier: License :: OSI Approved :: MIT License
Classifier: Programming Language :: Python :: 3
Requires-Python: >=3
Requires-Dist: garnett (>=0.7)
